xpip/__init__.py
xpip/cmds/__init__.py
xpip/cmds/build.py
xpip/cmds/setuptools.py
xpip/cmds/upload.py
xpip/cmds/version.py
xpip/utils/__init__.py
xpip/utils/attribute.py
xpip_python-1.3.dist-info/LICENSE
xpip_python-1.3.dist-info/METADATA
xpip_python-1.3.dist-info/WHEEL
xpip_python-1.3.dist-info/entry_points.txt
xpip_python-1.3.dist-info/top_level.txt
xpip_python-1.3.dist-info/zip-safe
xpip_python-1.3.dist-info/RECORD
